{
  "job_id": "job_886d720562154f1c",
  "status": {
    "job_id": "job_886d720562154f1c",
    "state": "failed",
    "intent_type": "job",
    "task_type": "schedule_cron_expression",
    "current_stage": "execute_local",
    "updated_at": "2026-04-09T20:51:10Z",
    "created_at": "2026-04-09T20:49:29Z"
  },
  "response": null,
  "evaluation": null,
  "error": {
    "job_id": "job_886d720562154f1c",
    "started_at": "2026-04-09T20:49:29Z",
    "error": {
      "code": "UNSUPPORTED_TASK_TYPE",
      "message": "Unsupported task_type: schedule_cron_expression",
      "details": {
        "task_type": "schedule_cron_expression",
        "verified": false,
        "executed_at": "2026-04-09T20:51:10Z",
        "execution_status": "failed",
        "details": {
          "code": "UNSUPPORTED_TASK_TYPE",
          "message": "Unsupported task_type: schedule_cron_expression",
          "parameters": {
            "schedule": {
              "cron_expression": "0 8 * * *",
              "timezone": "America/New_York",
              "days": "everyday",
              "command": "send_weather_update",
              "recipient": "user",
              "location": " Indianapolis"
            },
            "weather_source": "default_weather_api",
            "delivery_method": "email_or_notification",
            "target_time_reference": "daily 08:30 AM America/New_York"
          }
        }
      }
    }
  },
  "execution": {
    "task_type": "schedule_cron_expression",
    "verified": false,
    "executed_at": "2026-04-09T20:51:10Z",
    "execution_status": "failed",
    "details": {
      "code": "UNSUPPORTED_TASK_TYPE",
      "message": "Unsupported task_type: schedule_cron_expression",
      "parameters": {
        "schedule": {
          "cron_expression": "0 8 * * *",
          "timezone": "America/New_York",
          "days": "everyday",
          "command": "send_weather_update",
          "recipient": "user",
          "location": " Indianapolis"
        },
        "weather_source": "default_weather_api",
        "delivery_method": "email_or_notification",
        "target_time_reference": "daily 08:30 AM America/New_York"
      }
    }
  },
  "generated_at": "2026-04-09T20:51:10Z"
}
